cait/__init__.py
cait/_version.py
cait/data_handler.py
cait/evaluation_tools.py
cait/event_interface.py
cait/viztool.py
cait/augment/__init__.py
cait/augment/_cryoaug.py
cait/calibration/__init__.py
cait/calibration/_energy_calibration.py
cait/calibration/_energy_calibration_linear.py
cait/calibration/_energy_calibration_tree.py
cait/calibration/_pulser_model.py
cait/cuts/__init__.py
cait/cuts/_cut_class.py
cait/cuts/_logical.py
cait/cuts/_rate_cut.py
cait/cuts/_stability_cut.py
cait/data/__init__.py
cait/data/_baselines.py
cait/data/_converter.py
cait/data/_gen_h5.py
cait/data/_gen_h5_memsafe.py
cait/data/_merge_h5.py
cait/data/_raw.py
cait/data/_shrink_h5.py
cait/data/_test_data.py
cait/data/_xy_file.py
cait/datasets/__init__.py
cait/datasets/_pt_dataloader.py
cait/datasets/_pt_datamodule.py
cait/datasets/_pt_dataset.py
cait/datasets/_pt_sampler.py
cait/datasets/_pt_transforms.py
cait/evaluation/__init__.py
cait/evaluation/_color.py
cait/evaluation/_make_features.py
cait/evaluation/_pgf_config.py
cait/evaluation/_plot_event.py
cait/features/__init__.py
cait/features/_fem.py
cait/features/_mp.py
cait/features/_ph_corr.py
cait/filter/__init__.py
cait/filter/_extend.py
cait/filter/_ma.py
cait/filter/_of.py
cait/fit/__init__.py
cait/fit/_bl_fit.py
cait/fit/_noise.py
cait/fit/_numerical_fit.py
cait/fit/_pm_fit.py
cait/fit/_saturation.py
cait/fit/_sev.py
cait/fit/_templates.py
cait/fit/_threshold.py
cait/limit/__init__.py
cait/limit/_yellin.py
cait/mixins/__init__.py
cait/mixins/_data_handler_analysis.py
cait/mixins/_data_handler_bin.py
cait/mixins/_data_handler_csmpl.py
cait/mixins/_data_handler_features.py
cait/mixins/_data_handler_fit.py
cait/mixins/_data_handler_ml.py
cait/mixins/_data_handler_plot.py
cait/mixins/_data_handler_rdt.py
cait/mixins/_data_handler_simulate.py
cait/models/__init__.py
cait/models/_cnn_model.py
cait/models/_lstm_model.py
cait/models/_model_handler.py
cait/models/_predict.py
cait/models/_rnn_model.py
cait/models/_separation_lstm.py
cait-1.2.2.dist-info/LICENSE
cait-1.2.2.dist-info/METADATA
cait-1.2.2.dist-info/WHEEL
cait-1.2.2.dist-info/top_level.txt
cait-1.2.2.dist-info/RECORD
