Metadata-Version: 2.1
Name: cait
Version: 1.2.2
Summary: Cryogenic Artificial Intelligence Tools - A Python Package for the Data Analysis of Rare Event Search Experiments with Machine Learning.
Author-email: Philipp Schreiner <philipp.schreiner@oeaw.ac.at>, Felix Wagner <felix.wagner@oeaw.ac.at>
Project-URL: Repository, https://github.com/fewagner/cait
Project-URL: Documentation, https://cait.readthedocs.io/en/latest/index.html
Project-URL: Changelog, https://cait.readthedocs.io/en/latest/changelog.html
Classifier: Development Status :: 5 - Production/Stable
Classifier: Topic :: Scientific/Engineering :: Physics
Classifier: Programming Language :: Python :: 3
Classifier: License :: OSI Approved :: GNU General Public License v3 (GPLv3)
Classifier: Operating System :: OS Independent
Requires-Python: >=3.8
License-File: LICENSE
Requires-Dist: numpy >=1.22
Requires-Dist: scipy >=1.6
Requires-Dist: pandas >=1.1
Requires-Dist: h5py >=3.2
Requires-Dist: uproot >=4.1
Requires-Dist: ipywidgets >=7.5
Requires-Dist: dash >=2.0
Requires-Dist: matplotlib >=3.4
Requires-Dist: numba >=0.54
Requires-Dist: tqdm >=4.62
Requires-Dist: scikit-learn >=0.24
Requires-Dist: deprecation
Provides-Extra: clplot
Requires-Dist: uniplot >=0.12.2 ; extra == 'clplot'
Provides-Extra: nn
Requires-Dist: pytorch-lightning ==1.9.4 ; extra == 'nn'
Requires-Dist: torch >=1.8 ; extra == 'nn'
Provides-Extra: test
Requires-Dist: pytest ; extra == 'test'
